asyncserial/__init__.py
asyncserial/abstract_async_wrapper.py
asyncserial/async_serial_wrapper.py
asyncserial-0.1.0.dist-info/LICENSE.txt
asyncserial-0.1.0.dist-info/METADATA
asyncserial-0.1.0.dist-info/RECORD
asyncserial-0.1.0.dist-info/WHEEL
asyncserial-0.1.0.dist-info/top_level.txt
