Metadata-Version: 2.1
Name: asyncserial
Version: 0.1.0
Summary: Asyncio wrapper for pyserial
Home-page: https://github.com/xvzf/asyncserial-py
Author: Matthias Riegler
Author-email: matthias@xvzf.tech
License: UNKNOWN
Project-URL: Bug Reports, https://github.com/xvzf/asyncserial-py/issues
Project-URL: Source, https://github.com/xvzf/asyncserial-py/
Keywords: serial pyserial async asyncio
Platform: UNKNOWN
Classifier: Development Status :: 4 - Beta
Classifier: Intended Audience :: Developers
Classifier: License :: OSI Approved :: Apache Software License
Classifier: Framework :: AsyncIO
Classifier: Programming Language :: Python
Classifier: Programming Language :: Python :: 3
Classifier: Programming Language :: Python :: 3.5
Classifier: Programming Language :: Python :: 3.6
Requires-Python: >=3.5
Provides-Extra: uvloop support
